pytreenet/__init__.py
pytreenet/contractions/__init__.py
pytreenet/contractions/contraction_util.py
pytreenet/contractions/state_operator_contraction.py
pytreenet/contractions/state_state_contraction.py
pytreenet/contractions/tree_cach_dict.py
pytreenet/contractions/tree_contraction.py
pytreenet/core/__init__.py
pytreenet/core/canonical_form.py
pytreenet/core/graph_node.py
pytreenet/core/leg_specification.py
pytreenet/core/node.py
pytreenet/core/tree_structure.py
pytreenet/core/ttn.py
pytreenet/operators/__init__.py
pytreenet/operators/common_operators.py
pytreenet/operators/hamiltonian.py
pytreenet/operators/operator.py
pytreenet/operators/tensorproduct.py
pytreenet/random/__init__.py
pytreenet/random/random_hamiltonian.py
pytreenet/random/random_matrices.py
pytreenet/random/random_node.py
pytreenet/random/random_tensorproduct.py
pytreenet/random/random_ttns.py
pytreenet/special_ttn/__init__.py
pytreenet/special_ttn/fttn.py
pytreenet/special_ttn/mps.py
pytreenet/time_evolution/__init__.py
pytreenet/time_evolution/exact_time_evolution.py
pytreenet/time_evolution/tdvp.py
pytreenet/time_evolution/tebd.py
pytreenet/time_evolution/time_evolution.py
pytreenet/time_evolution/trotter.py
pytreenet/time_evolution/ttn_time_evolution.py
pytreenet/time_evolution/tdvp_algorithms/__init__.py
pytreenet/time_evolution/tdvp_algorithms/firstorderonesite.py
pytreenet/time_evolution/tdvp_algorithms/onesitetdvp.py
pytreenet/time_evolution/tdvp_algorithms/secondorderonesite.py
pytreenet/time_evolution/tdvp_algorithms/secondordertwosite.py
pytreenet/time_evolution/tdvp_algorithms/tdvp_algorithm.py
pytreenet/time_evolution/tdvp_algorithms/twositetdvp.py
pytreenet/time_evolution/time_evo_util/__init__.py
pytreenet/time_evolution/time_evo_util/update_path.py
pytreenet/ttno/__init__.py
pytreenet/ttno/collections.py
pytreenet/ttno/hyperedge.py
pytreenet/ttno/single_term_diagram.py
pytreenet/ttno/state_diagram.py
pytreenet/ttno/ttno_class.py
pytreenet/ttno/vertex.py
pytreenet/ttns/__init__.py
pytreenet-1.0.0.dist-info/LICENSE
pytreenet-1.0.0.dist-info/METADATA
pytreenet-1.0.0.dist-info/WHEEL
pytreenet-1.0.0.dist-info/top_level.txt
pytreenet-1.0.0.dist-info/RECORD
